apsw.cp36-win_amd64.pyd
apsw_wheels-3.36.0.post1.dist-info/LICENSE
apsw_wheels-3.36.0.post1.dist-info/METADATA
apsw_wheels-3.36.0.post1.dist-info/WHEEL
apsw_wheels-3.36.0.post1.dist-info/top_level.txt
apsw_wheels-3.36.0.post1.dist-info/RECORD
